dockerwatch/__init__.py
dockerwatch/main.py
dockerwatch/settings.py
dockerwatch/stats.py
dockerwatch/backends/__init__.py
dockerwatch/backends/cloudwatch.py
dockerwatch-0.0.1.dist-info/DESCRIPTION.rst
dockerwatch-0.0.1.dist-info/METADATA
dockerwatch-0.0.1.dist-info/RECORD
dockerwatch-0.0.1.dist-info/WHEEL
dockerwatch-0.0.1.dist-info/entry_points.txt
dockerwatch-0.0.1.dist-info/metadata.json
dockerwatch-0.0.1.dist-info/top_level.txt
