Metadata-Version: 2.0
Name: dockerwatch
Version: 0.0.1
Summary: Monitoring script for Docker
Home-page: https://github.com/hirokiky/dockerwatch
Author: Hiroki KIYOHARA
Author-email: hirokiky@gmail.com
License: MIT
Platform: UNKNOWN
Requires-Dist: docker (==2.6.1)
Requires-Dist: boto3 (==1.4.8)
